{
  "name": "Pont Kitchener-Marchand",
  "description": "Le compteur vélo du Pont Kitchener-Marchand la fréquentation cycliste du pont du même nom.",
  "arrondissement": "Lyon 2",
  "idPdc": 100031124,
  "coordinates": [
    4.8226442950519255,
    45.75139886296838
  ],
  "lines": [],
  "counts": [
    {
      "month": "2016-07-01",
      "count": 4743
    },
    {
      "month": "2016-08-01",
      "count": 9492
    },
    {
      "month": "2016-09-01",
      "count": 15647
    },
    {
      "month": "2016-10-01",
      "count": 11781
    },
    {
      "month": "2016-11-01",
      "count": 9687
    },
    {
      "month": "2016-12-01",
      "count": 9170
    },
    {
      "month": "2017-01-01",
      "count": 7834
    },
    {
      "month": "2017-02-01",
      "count": 9060
    },
    {
      "month": "2017-03-01",
      "count": 11770
    },
    {
      "month": "2017-04-01",
      "count": 11712
    },
    {
      "month": "2017-05-01",
      "count": 12189
    },
    {
      "month": "2017-06-01",
      "count": 13263
    },
    {
      "month": "2017-07-01",
      "count": 12060
    },
    {
      "month": "2017-08-01",
      "count": 10348
    },
    {
      "month": "2017-09-01",
      "count": 15679
    },
    {
      "month": "2017-10-01",
      "count": 17497
    },
    {
      "month": "2017-11-01",
      "count": 14670
    },
    {
      "month": "2017-12-01",
      "count": 9612
    },
    {
      "month": "2018-01-01",
      "count": 10741
    },
    {
      "month": "2018-02-01",
      "count": 8829
    },
    {
      "month": "2018-03-01",
      "count": 12370
    },
    {
      "month": "2018-04-01",
      "count": 14599
    },
    {
      "month": "2018-05-01",
      "count": 15296
    },
    {
      "month": "2018-06-01",
      "count": 15487
    },
    {
      "month": "2018-07-01",
      "count": 14753
    },
    {
      "month": "2018-08-01",
      "count": 12192
    },
    {
      "month": "2018-09-01",
      "count": 18961
    },
    {
      "month": "2018-10-01",
      "count": 17827
    },
    {
      "month": "2018-11-01",
      "count": 14711
    },
    {
      "month": "2018-12-01",
      "count": 11544
    },
    {
      "month": "2019-01-01",
      "count": 11785
    },
    {
      "month": "2019-02-01",
      "count": 11573
    },
    {
      "month": "2019-03-01",
      "count": 14863
    },
    {
      "month": "2019-04-01",
      "count": 12514
    },
    {
      "month": "2019-05-01",
      "count": 12084
    },
    {
      "month": "2019-06-01",
      "count": 12433
    },
    {
      "month": "2019-07-01",
      "count": 13768
    },
    {
      "month": "2019-08-01",
      "count": 11471
    },
    {
      "month": "2019-09-01",
      "count": 17536
    },
    {
      "month": "2019-10-01",
      "count": 17950
    },
    {
      "month": "2019-11-01",
      "count": 16412
    },
    {
      "month": "2019-12-01",
      "count": 14993
    },
    {
      "month": "2020-01-01",
      "count": 17025
    },
    {
      "month": "2020-02-01",
      "count": 18289
    },
    {
      "month": "2020-03-01",
      "count": 12318
    },
    {
      "month": "2020-04-01",
      "count": 6529
    },
    {
      "month": "2020-05-01",
      "count": 16684
    },
    {
      "month": "2020-06-01",
      "count": 23975
    },
    {
      "month": "2020-07-01",
      "count": 26400
    },
    {
      "month": "2020-08-01",
      "count": 19440
    },
    {
      "month": "2020-09-01",
      "count": 31100
    },
    {
      "month": "2020-10-01",
      "count": 24508
    },
    {
      "month": "2020-11-01",
      "count": 18286
    },
    {
      "month": "2020-12-01",
      "count": 14925
    },
    {
      "month": "2021-01-01",
      "count": 15975
    },
    {
      "month": "2021-02-01",
      "count": 17983
    },
    {
      "month": "2021-03-01",
      "count": 24324
    },
    {
      "month": "2021-04-01",
      "count": 22123
    },
    {
      "month": "2021-05-01",
      "count": 22978
    },
    {
      "month": "2021-06-01",
      "count": 28726
    },
    {
      "month": "2021-07-01",
      "count": 25062
    },
    {
      "month": "2021-08-01",
      "count": 21446
    },
    {
      "month": "2021-09-01",
      "count": 34198
    },
    {
      "month": "2021-10-01",
      "count": 30630
    },
    {
      "month": "2021-11-01",
      "count": 24553
    },
    {
      "month": "2021-12-01",
      "count": 18654
    },
    {
      "month": "2022-01-01",
      "count": 19378
    },
    {
      "month": "2022-02-01",
      "count": 21697
    },
    {
      "month": "2022-03-01",
      "count": 30294
    },
    {
      "month": "2022-04-01",
      "count": 25950
    },
    {
      "month": "2022-05-01",
      "count": 33912
    },
    {
      "month": "2022-06-01",
      "count": 30738
    },
    {
      "month": "2022-07-01",
      "count": 28014
    },
    {
      "month": "2022-08-01",
      "count": 21727
    },
    {
      "month": "2022-09-01",
      "count": 33597
    },
    {
      "month": "2022-10-01",
      "count": 33630
    },
    {
      "month": "2022-11-01",
      "count": 26348
    },
    {
      "month": "2022-12-01",
      "count": 18561
    },
    {
      "month": "2023-01-01",
      "count": 23849
    },
    {
      "month": "2023-02-01",
      "count": 22547
    },
    {
      "month": "2023-03-01",
      "count": 28536
    },
    {
      "month": "2023-04-01",
      "count": 25156
    },
    {
      "month": "2023-05-01",
      "count": 30602
    },
    {
      "month": "2023-06-01",
      "count": 32826
    },
    {
      "month": "2023-07-01",
      "count": 28455
    },
    {
      "month": "2023-08-01",
      "count": 22350
    },
    {
      "month": "2023-09-01",
      "count": 36212
    },
    {
      "month": "2023-10-01",
      "count": 33683
    },
    {
      "month": "2023-11-01",
      "count": 27248
    },
    {
      "month": "2023-12-01",
      "count": 21814
    },
    {
      "month": "2024-01-01",
      "count": 22915
    },
    {
      "month": "2024-02-01",
      "count": 25079
    },
    {
      "month": "2024-03-01",
      "count": 28803
    },
    {
      "month": "2024-04-01",
      "count": 26889
    },
    {
      "month": "2024-05-01",
      "count": 29016
    },
    {
      "month": "2024-06-01",
      "count": 31236
    },
    {
      "month": "2024-07-01",
      "count": 30890
    },
    {
      "month": "2024-08-01",
      "count": 23213
    }
  ]
}