{
  "date": "2022/11/01",
  "description": "Annonce du réaménagement des Ponts Lafayette et Morand dès 2023.",
  "imageUrl": "https://source.unsplash.com/KQJpAe6UabU",
  "events": [
    {
      "date": "2022/11/24",
      "news": [
        {
          "title": "Bruno Bernard, président la Métropole de Lyon, annonce que les pistes cyclables du Pont Lafayette et du Pont Morand seront réamnénagées en 2023. Une très bonne nouvelle pour les cyclistes lyonnais, mais aussi pour l'image de la ville puisque ces aménagements sont régulièrement raillés sur les réseaux sociaux.",
          "link": "voir le tweet",
          "tweet": "https://twitter.com/brunobernard_fr/status/1595818538803105792"
        }
      ]
    }
  ]
}
